pearldiver/__init__.py
pearldiver/__init__.py~
pearldiver/pearldiver.py
pearldiver/pearldiver.py~
pearldiver-1.0.0.dist-info/LICENSE
pearldiver-1.0.0.dist-info/WHEEL
pearldiver-1.0.0.dist-info/METADATA
pearldiver-1.0.0.dist-info/RECORD
