Metadata-Version: 1.2
Name: pearldiver
Version: 1.0.0
Summary: IOTA-PearlDiver - IOTA transaction nonce search
Home-page: https://github.com/mlouielu/iota-pearldiver
License: UNKNOWN
Author: Louie Lu
Author-email: git@louie.lu
Maintainer: Louie Lu
Maintainer-email: git@louie.lu
Requires-Python: >= 3
Classifier: License :: OSI Approved :: MIT License
Classifier: Programming Language :: Python :: 3
Classifier: Topic :: Software Development :: Libraries :: Python Modules
Classifier: Intended Audience :: Developers
Requires-Dist: pyota (>= 2.0.1)
